doubly_linked_list/__init__.py
doubly_linked_list/doubly_linked_list.py
doubly_linked_list/node.py
examples/__init__.py
examples/basic_usage.py
python_doubly_linked_list_lejacpcj-0.1.0.dist-info/licenses/LICENSE
python_doubly_linked_list_lejacpcj-0.1.0.dist-info/METADATA
python_doubly_linked_list_lejacpcj-0.1.0.dist-info/WHEEL
python_doubly_linked_list_lejacpcj-0.1.0.dist-info/top_level.txt
python_doubly_linked_list_lejacpcj-0.1.0.dist-info/RECORD
