Metadata-Version: 2.4
Name: python-doubly-linked-list-lejacpcj
Version: 0.1.0
Summary: A comprehensive, efficient, and easy-to-use doubly linked list implementation for Python
Author-email: Chia-Jung Wang <lejacp@gmail.com>
License: MIT
Project-URL: Homepage, https://github.com/lejacpCJ/python-doubly-linked-list
Project-URL: Documentation, https://github.com/lejacpCJ/python-doubly-linked-list#readme
Project-URL: Repository, https://github.com/lejacpCJ/python-doubly-linked-list.git
Project-URL: Bug Tracker, https://github.com/lejacpCJ/python-doubly-linked-list/issues
Keywords: data-structure,linked-list,doubly-linked-list,python
Classifier: Development Status :: 4 - Beta
Classifier: Intended Audience :: Developers
Classifier: License :: OSI Approved :: MIT License
Classifier: Operating System :: OS Independent
Classifier: Programming Language :: Python :: 3
Classifier: Programming Language :: Python :: 3.7
Classifier: Programming Language :: Python :: 3.8
Classifier: Programming Language :: Python :: 3.9
Classifier: Programming Language :: Python :: 3.10
Classifier: Programming Language :: Python :: 3.11
Classifier: Programming Language :: Python :: 3.12
Classifier: Topic :: Software Development :: Libraries :: Python Modules
Classifier: Topic :: Scientific/Engineering :: Information Analysis
Requires-Python: >=3.7
License-File: LICENSE
Provides-Extra: dev
Requires-Dist: pytest>=6.0; extra == "dev"
Requires-Dist: pytest-cov>=2.0; extra == "dev"
Requires-Dist: black>=22.0; extra == "dev"
Requires-Dist: isort>=5.0; extra == "dev"
Requires-Dist: flake8>=4.0; extra == "dev"
Requires-Dist: mypy>=0.900; extra == "dev"
Dynamic: license-file
